Workbook

Sheet README
B2: Marketing & Insight Analyst — Portfolio Workbook
B3: Sample project built on synthetic data for a multi-branch building materials distributor
B5: Tab | C5: What it shows
B6: KPI Definitions | C6: Standardised definitions for every metric used across this workbook.
B7: Data_Customers | C7: Cleaned customer data (600 customers).
B8: Data_Products | C8: Product catalogue with cost/price (31 products).
B9: Data_Orders | C9: Order headers, with customer type/branch pulled in via INDEX/MATCH.
B10: Data_OrderLines | C10: Order line detail, with product cost/category via INDEX/MATCH and a calculated margin column.
B11: Data_Campaigns | C11: Campaign metadata (8 campaigns).
B12: Data_CampaignSends | C12: Campaign send-level detail (516 sends) with opt-in cross-check.
B13: Lookup_Tool | C13: Type any Customer ID and instantly pull their profile + order history via INDEX/MATCH.
B14: Summary_BySegment | C14: Pivot-style summary: revenue, margin, margin % by customer type (SUMIFS).
B15: Summary_ByBranch | C15: Pivot-style summary: revenue by branch x product category (SUMIFS).
B16: Summary_CampaignROI | C16: Campaign performance: open/click/conversion rate, ROI (SUMIFS).
B18: Note on formulas
B19: This workbook uses INDEX/MATCH instead of XLOOKUP for all lookups. Functionally identical — both look up a value in one table and return a related value from another — but INDEX/MATCH is backward-compatible with older Excel versions, so it's the safer default for a workbook you don't control the recipient's Excel version for.

Sheet KPI_Definitions
B2: KPI Definitions
B3: Standardised metric definitions — the single source of truth for how each figure in this workbook is calculated.
B5: KPI / Term | C5: Definition | D5: Calculation Logic
B6: Active Customer | C6: A customer who has placed at least 1 order in the trailing 12 months. | D6: COUNTIFS(Orders, last 12 months) >= 1
B7: Repeat Purchase Rate | C7: % of customers with 2 or more lifetime orders, out of all customers with at least 1 order. | D7: COUNT(customers with order_count >= 2) / COUNT(customers with order_count >= 1)
B8: Gross Margin % | C8: Revenue minus cost of goods sold, divided by revenue. | D8: (Revenue - COGS) / Revenue
B9: Campaign ROI | C9: Net return on a campaign relative to its cost. | D9: (Revenue Generated - Campaign Cost) / Campaign Cost
B10: Open Rate | C10: % of sent messages that were opened. Not tracked for Direct Mail. | D10: Opens / Sends
B11: Conversion Rate | C11: % of sends that resulted in a purchase. | D11: Conversions / Sends
B12: NPS (Net Promoter Score) | C12: % Promoters minus % Detractors, from 0-10 survey scores (9-10=Promoter, 7-8=Passive, 0-6=Detractor). | D12: %Promoters - %Detractors
B13: Customer Segment: Champion | C13: Ordered within the last 90 days AND has 10+ lifetime orders. | D13: Recency <= 90 days AND Frequency >= 10
B14: Customer Segment: Loyal | C14: Ordered within the last 180 days AND has 5+ lifetime orders. | D14: Recency <= 180 days AND Frequency >= 5
B15: Customer Segment: At Risk / Dormant | C15: No order placed in over 365 days. | D15: Recency > 365 days
B16: Reference Date ('Today') | C16: The fixed 'as of' date used for all recency calculations in this workbook. | D16: 2026-07-07

Sheet Data_Customers
A1: Customer Id | B1: Customer Name | C1: Customer Type | D1: Branch | E1: Signup Date | F1: Email Opt In | G1: Sms Opt In
A2: C00001 | B2: Liam Evans | C2: Retail | D2: Binley (Coventry) | E2: 45155 | F2: 1 | G2: 1
A3: C00002 | B3: Jones & Sons | C3: Contractor | D3: Birmingham South | E3: 45359 | F3: 1 | G3: 1
A4: C00003 | B4: Smith Property Services | C4: Trade Account | D4: Birmingham South | E4: 45130 | F4: 1 | G4: 0
A5: C00004 | B5: Sam Walker | C5: Retail | D5: Northampton | E5: 45755 | F5: 0 | G5: 0
A6: C00005 | B6: Green Building Services | C6: Trade Account | D6: Northampton | E6: 45086 | F6: 1 | G6: 0
A7: C00006 | B7: Brown Home Improvements | C7: Trade Account | D7: Northampton | E7: 45794 | F7: 1 | G7: 1
A8: C00007 | B8: Turner Construction | C8: Trade Account | D8: Northampton | E8: 45314 | F8: 1 | G8: 1
A9: C00008 | B9: Sam Wilson | C9: Retail | D9: Leicester | E9: 45648 | F9: 1 | G9: 0
A10: C00009 | B10: Evans Construction | C10: Contractor | D10: Binley (Coventry) | E10: 45316 | F10: 1 | G10: 0
A11: C00010 | B11: Grace Wilson | C11: Retail | D11: Leicester | E11: 45613 | F11: 1 | G11: 0
A12: C00011 | B12: Priya Turner | C12: Retail | D12: Birmingham South | E12: 45673 | F12: 1 | G12: 1
A13: C00012 | B13: Turner Developments | C13: Trade Account | D13: Rugby | E13: 45628 | F13: 1 | G13: 0
... A601: C00600 | B601: Wright Contractors | C601: Contractor | D601: Rugby | E601: 45786 | F601: 0 | G601: 0

Sheet Data_Products
A1: Product Id | B1: Product Name | C1: Category | D1: Unit Cost | E1: Unit Price
A2: P0001 | B2: Treated Timber 47x100mm | C2: Timber | D2: 111.1 | E2: 135.95
A3: P0002 | B3: Sawn Timber 25x150mm | C3: Timber | D3: 168.32 | E3: 240.92
A4: P0003 | B4: OSB Board 18mm | C4: Timber | D4: 85.53 | E4: 122.01
A5: P0004 | B5: Plywood Sheet 12mm | C5: Timber | D5: 31.44 | E5: 49.15
A6: P0005 | B6: Roof Truss Timber | C6: Timber | D6: 59.07 | E6: 79.76
A7: P0006 | B7: General Purpose Cement 25kg | C7: Cement & Aggregates | D7: 51.51 | E7: 73.76
A8: P0007 | B8: Building Sand (Bulk Bag) | C8: Cement & Aggregates | D8: 99.99 | E8: 137.14
A9: P0008 | B9: Ballast (Bulk Bag) | C9: Cement & Aggregates | D9: 147.44 | E9: 184.05
A10: P0009 | B10: Postcrete 20kg | C10: Cement & Aggregates | D10: 81.07 | E10: 118.79
A11: P0010 | B11: Ready Mix Concrete (per m3) | C11: Cement & Aggregates | D11: 17.67 | E11: 25.23
A12: P0011 | B12: Loft Insulation Roll 100mm | C12: Insulation | D12: 58.26 | E12: 99.65
A13: P0012 | B13: Cavity Wall Batts | C13: Insulation | D13: 134.65 | E13: 165.07
... A32: P0031 | B32: Fence Post 2.4m | C32: Landscaping | D32: 36.87 | E32: 46.61

Sheet Data_Orders
A1: Order Id | B1: Customer Id | C1: Order Date | D1: Branch | E1: Order Total | F1: Customer Type (lookup) | G1: Customer Name (lookup)
A2: O000001 | B2: C00001 | C2: 45504 | D2: Binley (Coventry) | E2: 1873.59 | F2: =INDEX(Data_Customers!$C$2:$C$602,MATCH(B2,Data_Customers!$A$2:$A$602,0)) -> Retail | G2: =INDEX(Data_Customers!$B$2:$B$602,MATCH(B2,Data_Customers!$A$2:$A$602,0)) -> Liam Evans
A3: O000002 | B3: C00002 | C3: 45802 | D3: Birmingham South | E3: 308.04 | F3: =INDEX(Data_Customers!$C$2:$C$602,MATCH(B3,Data_Customers!$A$2:$A$602,0)) -> Contractor | G3: =INDEX(Data_Customers!$B$2:$B$602,MATCH(B3,Data_Customers!$A$2:$A$602,0)) -> Jones & Sons
A4: O000003 | B4: C00002 | C4: 45858 | D4: Birmingham South | E4: 7108.56 | F4: =INDEX(Data_Customers!$C$2:$C$602,MATCH(B4,Data_Customers!$A$2:$A$602,0)) -> Contractor | G4: =INDEX(Data_Customers!$B$2:$B$602,MATCH(B4,Data_Customers!$A$2:$A$602,0)) -> Jones & Sons
A5: O000004 | B5: C00002 | C5: 46040 | D5: Birmingham South | E5: 2802.4 | F5: =INDEX(Data_Customers!$C$2:$C$602,MATCH(B5,Data_Customers!$A$2:$A$602,0)) -> Contractor | G5: =INDEX(Data_Customers!$B$2:$B$602,MATCH(B5,Data_Customers!$A$2:$A$602,0)) -> Jones & Sons
A6: O000005 | B6: C00002 | C6: 46195 | D6: Birmingham South | E6: 7505.04 | F6: =INDEX(Data_Customers!$C$2:$C$602,MATCH(B6,Data_Customers!$A$2:$A$602,0)) -> Contractor | G6: =INDEX(Data_Customers!$B$2:$B$602,MATCH(B6,Data_Customers!$A$2:$A$602,0)) -> Jones & Sons
A7: O000006 | B7: C00002 | C7: 45572 | D7: Birmingham South | E7: 5939.52 | F7: =INDEX(Data_Customers!$C$2:$C$602,MATCH(B7,Data_Customers!$A$2:$A$602,0)) -> Contractor | G7: =INDEX(Data_Customers!$B$2:$B$602,MATCH(B7,Data_Customers!$A$2:$A$602,0)) -> Jones & Sons
A8: O000007 | B8: C00002 | C8: 46008 | D8: Birmingham South | E8: 4957.26 | F8: =INDEX(Data_Customers!$C$2:$C$602,MATCH(B8,Data_Customers!$A$2:$A$602,0)) -> Contractor | G8: =INDEX(Data_Customers!$B$2:$B$602,MATCH(B8,Data_Customers!$A$2:$A$602,0)) -> Jones & Sons
A9: O000008 | B9: C00002 | C9: 45931 | D9: Birmingham South | E9: 3550.84 | F9: =INDEX(Data_Customers!$C$2:$C$602,MATCH(B9,Data_Customers!$A$2:$A$602,0)) -> Contractor | G9: =INDEX(Data_Customers!$B$2:$B$602,MATCH(B9,Data_Customers!$A$2:$A$602,0)) -> Jones & Sons
A10: O000009 | B10: C00002 | C10: 45847 | D10: Birmingham South | E10: 3690.34 | F10: =INDEX(Data_Customers!$C$2:$C$602,MATCH(B10,Data_Customers!$A$2:$A$602,0)) -> Contractor | G10: =INDEX(Data_Customers!$B$2:$B$602,MATCH(B10,Data_Customers!$A$2:$A$602,0)) -> Jones & Sons
A11: O000010 | B11: C00002 | C11: 45888 | D11: Birmingham South | E11: 6693 | F11: =INDEX(Data_Customers!$C$2:$C$602,MATCH(B11,Data_Customers!$A$2:$A$602,0)) -> Contractor | G11: =INDEX(Data_Customers!$B$2:$B$602,MATCH(B11,Data_Customers!$A$2:$A$602,0)) -> Jones & Sons
A12: O000011 | B12: C00002 | C12: 45401 | D12: Birmingham South | E12: 454.85 | F12: =INDEX(Data_Customers!$C$2:$C$602,MATCH(B12,Data_Customers!$A$2:$A$602,0)) -> Contractor | G12: =INDEX(Data_Customers!$B$2:$B$602,MATCH(B12,Data_Customers!$A$2:$A$602,0)) -> Jones & Sons
A13: O000012 | B13: C00002 | C13: 45346 | D13: Birmingham South | E13: 1234.26 | F13: =INDEX(Data_Customers!$C$2:$C$602,MATCH(B13,Data_Customers!$A$2:$A$602,0)) -> Contractor | G13: =INDEX(Data_Customers!$B$2:$B$602,MATCH(B13,Data_Customers!$A$2:$A$602,0)) -> Jones & Sons
... A4726: O004725 | B4726: C00600 | C4726: 45441 | D4726: Rugby | E4726: 7745.76 | F4726: =INDEX(Data_Customers!$C$2:$C$602,MATCH(B4726,Data_Customers!$A$2:$A$602,0)) -> Contractor | G4726: =INDEX(Data_Customers!$B$2:$B$602,MATCH(B4726,Data_Customers!$A$2:$A$602,0)) -> Wright Contractors

Sheet Data_OrderLines
A1: Order Line Id | B1: Order Id | C1: Product Id | D1: Quantity | E1: Unit Price | F1: Line Total | G1: Unit Cost (lookup) | H1: Category (lookup) | I1: Margin ($) | J1: Margin (%) | K1: Customer Type (via Order) | L1: Branch (via Order)
A2: OL000001 | B2: O000001 | C2: P0030 | D2: 19 | E2: 98.61 | F2: 1873.59 | G2: =INDEX(Data_Products!$D$2:$D$33,MATCH(C2,Data_Products!$A$2:$A$33,0)) -> 74.84 | H2: =INDEX(Data_Products!$C$2:$C$33,MATCH(C2,Data_Products!$A$2:$A$33,0)) -> Landscaping | I2: =D2*(E2-G2) -> 451.63 | J2: =IFERROR(I2/F2,0) -> 0.2410506 | K2: =IFERROR(INDEX(Data_Orders!$F$2:$F$4727,MATCH(B2,Data_Orders!$A$2:$A$4727,0)),"") -> Retail | L2: =IFERROR(INDEX(Data_Orders!$D$2:$D$4727,MATCH(B2,Data_Orders!$A$2:$A$4727,0)),"") -> Binley (Coventry)
A3: OL000002 | B3: O000002 | C3: P0017 | D3: 2 | E3: 154.02 | F3: 308.04 | G3: =INDEX(Data_Products!$D$2:$D$33,MATCH(C3,Data_Products!$A$2:$A$33,0)) -> 102.1 | H3: =INDEX(Data_Products!$C$2:$C$33,MATCH(C3,Data_Products!$A$2:$A$33,0)) -> Tools & Fixings | I3: =D3*(E3-G3) -> 103.84 | J3: =IFERROR(I3/F3,0) -> 0.33709908 | K3: =IFERROR(INDEX(Data_Orders!$F$2:$F$4727,MATCH(B3,Data_Orders!$A$2:$A$4727,0)),"") -> Contractor | L3: =IFERROR(INDEX(Data_Orders!$D$2:$D$4727,MATCH(B3,Data_Orders!$A$2:$A$4727,0)),"") -> Birmingham South
A4: OL000003 | B4: O000003 | C4: P0027 | D4: 17 | E4: 86.28 | F4: 1466.76 | G4: =INDEX(Data_Products!$D$2:$D$33,MATCH(C4,Data_Products!$A$2:$A$33,0)) -> 68.55 | H4: =INDEX(Data_Products!$C$2:$C$33,MATCH(C4,Data_Products!$A$2:$A$33,0)) -> Plumbing & Drainage | I4: =D4*(E4-G4) -> 301.41 | J4: =IFERROR(I4/F4,0) -> 0.20549374 | K4: =IFERROR(INDEX(Data_Orders!$F$2:$F$4727,MATCH(B4,Data_Orders!$A$2:$A$4727,0)),"") -> Contractor | L4: =IFERROR(INDEX(Data_Orders!$D$2:$D$4727,MATCH(B4,Data_Orders!$A$2:$A$4727,0)),"") -> Birmingham South
A5: OL000004 | B5: O000003 | C5: P0019 | D5: 6 | E5: 238.63 | F5: 1431.78 | G5: =INDEX(Data_Products!$D$2:$D$33,MATCH(C5,Data_Products!$A$2:$A$33,0)) -> 148.91 | H5: =INDEX(Data_Products!$C$2:$C$33,MATCH(C5,Data_Products!$A$2:$A$33,0)) -> Tools & Fixings | I5: =D5*(E5-G5) -> 538.32 | J5: =IFERROR(I5/F5,0) -> 0.37597955 | K5: =IFERROR(INDEX(Data_Orders!$F$2:$F$4727,MATCH(B5,Data_Orders!$A$2:$A$4727,0)),"") -> Contractor | L5: =IFERROR(INDEX(Data_Orders!$D$2:$D$4727,MATCH(B5,Data_Orders!$A$2:$A$4727,0)),"") -> Birmingham South
A6: OL000005 | B6: O000003 | C6: P0016 | D6: 19 | E6: 190.44 | F6: 3618.36 | G6: =INDEX(Data_Products!$D$2:$D$33,MATCH(C6,Data_Products!$A$2:$A$33,0)) -> 115.48 | H6: =INDEX(Data_Products!$C$2:$C$33,MATCH(C6,Data_Products!$A$2:$A$33,0)) -> Tools & Fixings | I6: =D6*(E6-G6) -> 1424.24 | J6: =IFERROR(I6/F6,0) -> 0.39361479 | K6: =IFERROR(INDEX(Data_Orders!$F$2:$F$4727,MATCH(B6,Data_Orders!$A$2:$A$4727,0)),"") -> Contractor | L6: =IFERROR(INDEX(Data_Orders!$D$2:$D$4727,MATCH(B6,Data_Orders!$A$2:$A$4727,0)),"") -> Birmingham South
A7: OL000006 | B7: O000003 | C7: P0030 | D7: 6 | E7: 98.61 | F7: 591.66 | G7: =INDEX(Data_Products!$D$2:$D$33,MATCH(C7,Data_Products!$A$2:$A$33,0)) -> 74.84 | H7: =INDEX(Data_Products!$C$2:$C$33,MATCH(C7,Data_Products!$A$2:$A$33,0)) -> Landscaping | I7: =D7*(E7-G7) -> 142.62 | J7: =IFERROR(I7/F7,0) -> 0.2410506 | K7: =IFERROR(INDEX(Data_Orders!$F$2:$F$4727,MATCH(B7,Data_Orders!$A$2:$A$4727,0)),"") -> Contractor | L7: =IFERROR(INDEX(Data_Orders!$D$2:$D$4727,MATCH(B7,Data_Orders!$A$2:$A$4727,0)),"") -> Birmingham South
A8: OL000007 | B8: O000004 | C8: P0004 | D8: 20 | E8: 49.15 | F8: 983 | G8: =INDEX(Data_Products!$D$2:$D$33,MATCH(C8,Data_Products!$A$2:$A$33,0)) -> 31.44 | H8: =INDEX(Data_Products!$C$2:$C$33,MATCH(C8,Data_Products!$A$2:$A$33,0)) -> Timber | I8: =D8*(E8-G8) -> 354.2 | J8: =IFERROR(I8/F8,0) -> 0.36032553 | K8: =IFERROR(INDEX(Data_Orders!$F$2:$F$4727,MATCH(B8,Data_Orders!$A$2:$A$4727,0)),"") -> Contractor | L8: =IFERROR(INDEX(Data_Orders!$D$2:$D$4727,MATCH(B8,Data_Orders!$A$2:$A$4727,0)),"") -> Birmingham South
A9: OL000008 | B9: O000004 | C9: P0013 | D9: 20 | E9: 90.97 | F9: 1819.4 | G9: =INDEX(Data_Products!$D$2:$D$33,MATCH(C9,Data_Products!$A$2:$A$33,0)) -> 73.81 | H9: =INDEX(Data_Products!$C$2:$C$33,MATCH(C9,Data_Products!$A$2:$A$33,0)) -> Insulation | I9: =D9*(E9-G9) -> 343.2 | J9: =IFERROR(I9/F9,0) -> 0.18863362 | K9: =IFERROR(INDEX(Data_Orders!$F$2:$F$4727,MATCH(B9,Data_Orders!$A$2:$A$4727,0)),"") -> Contractor | L9: =IFERROR(INDEX(Data_Orders!$D$2:$D$4727,MATCH(B9,Data_Orders!$A$2:$A$4727,0)),"") -> Birmingham South
A10: OL000009 | B10: O000005 | C10: P0017 | D10: 14 | E10: 154.02 | F10: 2156.28 | G10: =INDEX(Data_Products!$D$2:$D$33,MATCH(C10,Data_Products!$A$2:$A$33,0)) -> 102.1 | H10: =INDEX(Data_Products!$C$2:$C$33,MATCH(C10,Data_Products!$A$2:$A$33,0)) -> Tools & Fixings | I10: =D10*(E10-G10) -> 726.88 | J10: =IFERROR(I10/F10,0) -> 0.33709908 | K10: =IFERROR(INDEX(Data_Orders!$F$2:$F$4727,MATCH(B10,Data_Orders!$A$2:$A$4727,0)),"") -> Contractor | L10: =IFERROR(INDEX(Data_Orders!$D$2:$D$4727,MATCH(B10,Data_Orders!$A$2:$A$4727,0)),"") -> Birmingham South
A11: OL000010 | B11: O000005 | C11: P0029 | D11: 20 | E11: 231.05 | F11: 4621 | G11: =INDEX(Data_Products!$D$2:$D$33,MATCH(C11,Data_Products!$A$2:$A$33,0)) -> 148.29 | H11: =INDEX(Data_Products!$C$2:$C$33,MATCH(C11,Data_Products!$A$2:$A$33,0)) -> Landscaping | I11: =D11*(E11-G11) -> 1655.2 | J11: =IFERROR(I11/F11,0) -> 0.35819087 | K11: =IFERROR(INDEX(Data_Orders!$F$2:$F$4727,MATCH(B11,Data_Orders!$A$2:$A$4727,0)),"") -> Contractor | L11: =IFERROR(INDEX(Data_Orders!$D$2:$D$4727,MATCH(B11,Data_Orders!$A$2:$A$4727,0)),"") -> Birmingham South
A12: OL000011 | B12: O000005 | C12: P0013 | D12: 8 | E12: 90.97 | F12: 727.76 | G12: =INDEX(Data_Products!$D$2:$D$33,MATCH(C12,Data_Products!$A$2:$A$33,0)) -> 73.81 | H12: =INDEX(Data_Products!$C$2:$C$33,MATCH(C12,Data_Products!$A$2:$A$33,0)) -> Insulation | I12: =D12*(E12-G12) -> 137.28 | J12: =IFERROR(I12/F12,0) -> 0.18863362 | K12: =IFERROR(INDEX(Data_Orders!$F$2:$F$4727,MATCH(B12,Data_Orders!$A$2:$A$4727,0)),"") -> Contractor | L12: =IFERROR(INDEX(Data_Orders!$D$2:$D$4727,MATCH(B12,Data_Orders!$A$2:$A$4727,0)),"") -> Birmingham South
A13: OL000012 | B13: O000006 | C13: P0031 | D13: 5 | E13: 46.61 | F13: 233.05 | G13: =INDEX(Data_Products!$D$2:$D$33,MATCH(C13,Data_Products!$A$2:$A$33,0)) -> 36.87 | H13: =INDEX(Data_Products!$C$2:$C$33,MATCH(C13,Data_Products!$A$2:$A$33,0)) -> Landscaping | I13: =D13*(E13-G13) -> 48.7 | J13: =IFERROR(I13/F13,0) -> 0.20896803 | K13: =IFERROR(INDEX(Data_Orders!$F$2:$F$4727,MATCH(B13,Data_Orders!$A$2:$A$4727,0)),"") -> Contractor | L13: =IFERROR(INDEX(Data_Orders!$D$2:$D$4727,MATCH(B13,Data_Orders!$A$2:$A$4727,0)),"") -> Birmingham South
... A14099: OL014098 | B14099: O004725 | C14099: P0016 | D14099: 12 | E14099: 190.44 | F14099: 2285.28 | G14099: =INDEX(Data_Products!$D$2:$D$33,MATCH(C14099,Data_Products!$A$2:$A$33,0)) -> 115.48 | H14099: =INDEX(Data_Products!$C$2:$C$33,MATCH(C14099,Data_Products!$A$2:$A$33,0)) -> Tools & Fixings | I14099: =D14099*(E14099-G14099) -> 899.52 | J14099: =IFERROR(I14099/F14099,0) -> 0.39361479 | K14099: =IFERROR(INDEX(Data_Orders!$F$2:$F$4727,MATCH(B14099,Data_Orders!$A$2:$A$4727,0)),"") -> Contractor | L14099: =IFERROR(INDEX(Data_Orders!$D$2:$D$4727,MATCH(B14099,Data_Orders!$A$2:$A$4727,0)),"") -> Rugby

Sheet Data_Campaigns
A1: Campaign Id | B1: Campaign Name | C1: Channel | D1: Target Segment | E1: Send Date | F1: Campaign Cost
A2: CAMP001 | B2: Spring Trade Promo | C2: Email | D2: Trade Account | E2: 45607 | F2: 2135.44
A3: CAMP002 | B3: Loft Insulation Push | C3: Email | D3: Retail | E3: 45475 | F3: 463.88
A4: CAMP003 | B4: Contractor Loyalty Rewards | C4: SMS | D4: Contractor | E4: 45323 | F4: 445.65
A5: CAMP004 | B5: New Account Welcome Series | C5: Email | D5: Trade Account | E5: 45859 | F5: 2039.3
A6: CAMP005 | B6: Summer Landscaping Sale | C6: Direct Mail | D6: Retail | E6: 45839 | F6: 1455.1
A7: CAMP006 | B7: Housebuilder Bulk Discount | C7: Email | D7: Housebuilder | E7: 45977 | F7: 1614.39
A8: CAMP007 | B8: Winter Roofing Materials Offer | C8: SMS | D8: Contractor | E8: 45947 | F8: 2255.4
A9: CAMP008 | B9: Cement & Aggregates Flash Sale | C9: Email | D9: Retail | E9: 45959 | F9: 1675.45

Sheet Data_CampaignSends
A1: Send Id | B1: Campaign Id | C1: Customer Id | D1: Opened | E1: Clicked | F1: Converted | G1: Revenue Generated | H1: Channel (lookup) | I1: Customer Type (lookup)
A2: S000001 | B2: CAMP001 | C2: C00150 | D2: 1 | E2: 0 | F2: 0 | G2: 0 | H2: =INDEX(Data_Campaigns!$C$2:$C$10,MATCH(B2,Data_Campaigns!$A$2:$A$10,0)) -> Email | I2: =INDEX(Data_Customers!$C$2:$C$602,MATCH(C2,Data_Customers!$A$2:$A$602,0)) -> Trade Account
A3: S000002 | B3: CAMP001 | C3: C00549 | D3: 0 | E3: 0 | F3: 0 | G3: 0 | H3: =INDEX(Data_Campaigns!$C$2:$C$10,MATCH(B3,Data_Campaigns!$A$2:$A$10,0)) -> Email | I3: =INDEX(Data_Customers!$C$2:$C$602,MATCH(C3,Data_Customers!$A$2:$A$602,0)) -> Trade Account
A4: S000003 | B4: CAMP001 | C4: C00516 | D4: 0 | E4: 0 | F4: 0 | G4: 0 | H4: =INDEX(Data_Campaigns!$C$2:$C$10,MATCH(B4,Data_Campaigns!$A$2:$A$10,0)) -> Email | I4: =INDEX(Data_Customers!$C$2:$C$602,MATCH(C4,Data_Customers!$A$2:$A$602,0)) -> Trade Account
A5: S000004 | B5: CAMP001 | C5: C00235 | D5: 0 | E5: 0 | F5: 0 | G5: 0 | H5: =INDEX(Data_Campaigns!$C$2:$C$10,MATCH(B5,Data_Campaigns!$A$2:$A$10,0)) -> Email | I5: =INDEX(Data_Customers!$C$2:$C$602,MATCH(C5,Data_Customers!$A$2:$A$602,0)) -> Trade Account
A6: S000005 | B6: CAMP001 | C6: C00353 | D6: 0 | E6: 0 | F6: 0 | G6: 0 | H6: =INDEX(Data_Campaigns!$C$2:$C$10,MATCH(B6,Data_Campaigns!$A$2:$A$10,0)) -> Email | I6: =INDEX(Data_Customers!$C$2:$C$602,MATCH(C6,Data_Customers!$A$2:$A$602,0)) -> Trade Account
A7: S000006 | B7: CAMP001 | C7: C00443 | D7: 0 | E7: 0 | F7: 0 | G7: 0 | H7: =INDEX(Data_Campaigns!$C$2:$C$10,MATCH(B7,Data_Campaigns!$A$2:$A$10,0)) -> Email | I7: =INDEX(Data_Customers!$C$2:$C$602,MATCH(C7,Data_Customers!$A$2:$A$602,0)) -> Trade Account
A8: S000007 | B8: CAMP001 | C8: C00315 | D8: 1 | E8: 0 | F8: 0 | G8: 0 | H8: =INDEX(Data_Campaigns!$C$2:$C$10,MATCH(B8,Data_Campaigns!$A$2:$A$10,0)) -> Email | I8: =INDEX(Data_Customers!$C$2:$C$602,MATCH(C8,Data_Customers!$A$2:$A$602,0)) -> Trade Account
A9: S000008 | B9: CAMP001 | C9: C00208 | D9: 0 | E9: 0 | F9: 0 | G9: 0 | H9: =INDEX(Data_Campaigns!$C$2:$C$10,MATCH(B9,Data_Campaigns!$A$2:$A$10,0)) -> Email | I9: =INDEX(Data_Customers!$C$2:$C$602,MATCH(C9,Data_Customers!$A$2:$A$602,0)) -> Trade Account
A10: S000009 | B10: CAMP001 | C10: C00480 | D10: 1 | E10: 1 | F10: 0 | G10: 0 | H10: =INDEX(Data_Campaigns!$C$2:$C$10,MATCH(B10,Data_Campaigns!$A$2:$A$10,0)) -> Email | I10: =INDEX(Data_Customers!$C$2:$C$602,MATCH(C10,Data_Customers!$A$2:$A$602,0)) -> Trade Account
A11: S000010 | B11: CAMP001 | C11: C00305 | D11: 0 | E11: 0 | F11: 0 | G11: 0 | H11: =INDEX(Data_Campaigns!$C$2:$C$10,MATCH(B11,Data_Campaigns!$A$2:$A$10,0)) -> Email | I11: =INDEX(Data_Customers!$C$2:$C$602,MATCH(C11,Data_Customers!$A$2:$A$602,0)) -> Trade Account
A12: S000011 | B12: CAMP001 | C12: C00465 | D12: 0 | E12: 0 | F12: 0 | G12: 0 | H12: =INDEX(Data_Campaigns!$C$2:$C$10,MATCH(B12,Data_Campaigns!$A$2:$A$10,0)) -> Email | I12: =INDEX(Data_Customers!$C$2:$C$602,MATCH(C12,Data_Customers!$A$2:$A$602,0)) -> Trade Account
A13: S000012 | B13: CAMP001 | C13: C00074 | D13: 0 | E13: 0 | F13: 0 | G13: 0 | H13: =INDEX(Data_Campaigns!$C$2:$C$10,MATCH(B13,Data_Campaigns!$A$2:$A$10,0)) -> Email | I13: =INDEX(Data_Customers!$C$2:$C$602,MATCH(C13,Data_Customers!$A$2:$A$602,0)) -> Trade Account
... A193: S000192 | B193: CAMP004 | C193: C00104 | D193: 1 | E193: 0 | F193: 0 | G193: 0 | H193: =INDEX(Data_Campaigns!$C$2:$C$10,MATCH(B193,Data_Campaigns!$A$2:$A$10,0)) -> Email | I193: =INDEX(Data_Customers!$C$2:$C$602,MATCH(C193,Data_Customers!$A$2:$A$602,0)) -> Trade Account
A194: S000193 | B194: CAMP005 | C194: C00421 | E194: 0 | F194: 0 | G194: 0 | H194: =INDEX(Data_Campaigns!$C$2:$C$10,MATCH(B194,Data_Campaigns!$A$2:$A$10,0)) -> Direct Mail | I194: =INDEX(Data_Customers!$C$2:$C$602,MATCH(C194,Data_Customers!$A$2:$A$602,0)) -> Retail
A195: S000194 | B195: CAMP005 | C195: C00210 | E195: 0 | F195: 0 | G195: 0 | H195: =INDEX(Data_Campaigns!$C$2:$C$10,MATCH(B195,Data_Campaigns!$A$2:$A$10,0)) -> Direct Mail | I195: =INDEX(Data_Customers!$C$2:$C$602,MATCH(C195,Data_Customers!$A$2:$A$602,0)) -> Retail
A196: S000195 | B196: CAMP005 | C196: C00098 | E196: 0 | F196: 0 | G196: 0 | H196: =INDEX(Data_Campaigns!$C$2:$C$10,MATCH(B196,Data_Campaigns!$A$2:$A$10,0)) -> Direct Mail | I196: =INDEX(Data_Customers!$C$2:$C$602,MATCH(C196,Data_Customers!$A$2:$A$602,0)) -> Retail
A197: S000196 | B197: CAMP005 | C197: C00029 | E197: 0 | F197: 0 | G197: 0 | H197: =INDEX(Data_Campaigns!$C$2:$C$10,MATCH(B197,Data_Campaigns!$A$2:$A$10,0)) -> Direct Mail | I197: =INDEX(Data_Customers!$C$2:$C$602,MATCH(C197,Data_Customers!$A$2:$A$602,0)) -> Retail
A198: S000197 | B198: CAMP005 | C198: C00562 | E198: 0 | F198: 0 | G198: 0 | H198: =INDEX(Data_Campaigns!$C$2:$C$10,MATCH(B198,Data_Campaigns!$A$2:$A$10,0)) -> Direct Mail | I198: =INDEX(Data_Customers!$C$2:$C$602,MATCH(C198,Data_Customers!$A$2:$A$602,0)) -> Retail
A199: S000198 | B199: CAMP005 | C199: C00350 | E199: 0 | F199: 0 | G199: 0 | H199: =INDEX(Data_Campaigns!$C$2:$C$10,MATCH(B199,Data_Campaigns!$A$2:$A$10,0)) -> Direct Mail | I199: =INDEX(Data_Customers!$C$2:$C$602,MATCH(C199,Data_Customers!$A$2:$A$602,0)) -> Retail
A200: S000199 | B200: CAMP005 | C200: C00106 | E200: 0 | F200: 0 | G200: 0 | H200: =INDEX(Data_Campaigns!$C$2:$C$10,MATCH(B200,Data_Campaigns!$A$2:$A$10,0)) -> Direct Mail | I200: =INDEX(Data_Customers!$C$2:$C$602,MATCH(C200,Data_Customers!$A$2:$A$602,0)) -> Retail
A201: S000200 | B201: CAMP005 | C201: C00536 | E201: 0 | F201: 0 | G201: 0 | H201: =INDEX(Data_Campaigns!$C$2:$C$10,MATCH(B201,Data_Campaigns!$A$2:$A$10,0)) -> Direct Mail | I201: =INDEX(Data_Customers!$C$2:$C$602,MATCH(C201,Data_Customers!$A$2:$A$602,0)) -> Retail
A202: S000201 | B202: CAMP005 | C202: C00534 | E202: 0 | F202: 0 | G202: 0 | H202: =INDEX(Data_Campaigns!$C$2:$C$10,MATCH(B202,Data_Campaigns!$A$2:$A$10,0)) -> Direct Mail | I202: =INDEX(Data_Customers!$C$2:$C$602,MATCH(C202,Data_Customers!$A$2:$A$602,0)) -> Retail
A203: S000202 | B203: CAMP005 | C203: C00088 | E203: 0 | F203: 0 | G203: 0 | H203: =INDEX(Data_Campaigns!$C$2:$C$10,MATCH(B203,Data_Campaigns!$A$2:$A$10,0)) -> Direct Mail | I203: =INDEX(Data_Customers!$C$2:$C$602,MATCH(C203,Data_Customers!$A$2:$A$602,0)) -> Retail
A204: S000203 | B204: CAMP005 | C204: C00530 | E204: 0 | F204: 0 | G204: 0 | H204: =INDEX(Data_Campaigns!$C$2:$C$10,MATCH(B204,Data_Campaigns!$A$2:$A$10,0)) -> Direct Mail | I204: =INDEX(Data_Customers!$C$2:$C$602,MATCH(C204,Data_Customers!$A$2:$A$602,0)) -> Retail
A205: S000204 | B205: CAMP005 | C205: C00166 | E205: 0 | F205: 0 | G205: 0 | H205: =INDEX(Data_Campaigns!$C$2:$C$10,MATCH(B205,Data_Campaigns!$A$2:$A$10,0)) -> Direct Mail | I205: =INDEX(Data_Customers!$C$2:$C$602,MATCH(C205,Data_Customers!$A$2:$A$602,0)) -> Retail
... A281: S000280 | B281: CAMP005 | C281: C00219 | E281: 0 | F281: 0 | G281: 0 | H281: =INDEX(Data_Campaigns!$C$2:$C$10,MATCH(B281,Data_Campaigns!$A$2:$A$10,0)) -> Direct Mail | I281: =INDEX(Data_Customers!$C$2:$C$602,MATCH(C281,Data_Customers!$A$2:$A$602,0)) -> Retail
A282: S000281 | B282: CAMP006 | C282: C00488 | D282: 1 | E282: 0 | F282: 0 | G282: 0 | H282: =INDEX(Data_Campaigns!$C$2:$C$10,MATCH(B282,Data_Campaigns!$A$2:$A$10,0)) -> Email | I282: =INDEX(Data_Customers!$C$2:$C$602,MATCH(C282,Data_Customers!$A$2:$A$602,0)) -> Housebuilder
A283: S000282 | B283: CAMP006 | C283: C00046 | D283: 0 | E283: 0 | F283: 0 | G283: 0 | H283: =INDEX(Data_Campaigns!$C$2:$C$10,MATCH(B283,Data_Campaigns!$A$2:$A$10,0)) -> Email | I283: =INDEX(Data_Customers!$C$2:$C$602,MATCH(C283,Data_Customers!$A$2:$A$602,0)) -> Housebuilder
A284: S000283 | B284: CAMP006 | C284: C00227 | D284: 0 | E284: 0 | F284: 0 | G284: 0 | H284: =INDEX(Data_Campaigns!$C$2:$C$10,MATCH(B284,Data_Campaigns!$A$2:$A$10,0)) -> Email | I284: =INDEX(Data_Customers!$C$2:$C$602,MATCH(C284,Data_Customers!$A$2:$A$602,0)) -> Housebuilder
A285: S000284 | B285: CAMP006 | C285: C00558 | D285: 0 | E285: 0 | F285: 0 | G285: 0 | H285: =INDEX(Data_Campaigns!$C$2:$C$10,MATCH(B285,Data_Campaigns!$A$2:$A$10,0)) -> Email | I285: =INDEX(Data_Customers!$C$2:$C$602,MATCH(C285,Data_Customers!$A$2:$A$602,0)) -> Housebuilder
A286: S000285 | B286: CAMP006 | C286: C00556 | D286: 0 | E286: 0 | F286: 0 | G286: 0 | H286: =INDEX(Data_Campaigns!$C$2:$C$10,MATCH(B286,Data_Campaigns!$A$2:$A$10,0)) -> Email | I286: =INDEX(Data_Customers!$C$2:$C$602,MATCH(C286,Data_Customers!$A$2:$A$602,0)) -> Housebuilder
A287: S000286 | B287: CAMP006 | C287: C00417 | D287: 1 | E287: 0 | F287: 0 | G287: 0 | H287: =INDEX(Data_Campaigns!$C$2:$C$10,MATCH(B287,Data_Campaigns!$A$2:$A$10,0)) -> Email | I287: =INDEX(Data_Customers!$C$2:$C$602,MATCH(C287,Data_Customers!$A$2:$A$602,0)) -> Housebuilder
A288: S000287 | B288: CAMP006 | C288: C00474 | D288: 0 | E288: 0 | F288: 0 | G288: 0 | H288: =INDEX(Data_Campaigns!$C$2:$C$10,MATCH(B288,Data_Campaigns!$A$2:$A$10,0)) -> Email | I288: =INDEX(Data_Customers!$C$2:$C$602,MATCH(C288,Data_Customers!$A$2:$A$602,0)) -> Housebuilder
A289: S000288 | B289: CAMP006 | C289: C00064 | D289: 0 | E289: 0 | F289: 0 | G289: 0 | H289: =INDEX(Data_Campaigns!$C$2:$C$10,MATCH(B289,Data_Campaigns!$A$2:$A$10,0)) -> Email | I289: =INDEX(Data_Customers!$C$2:$C$602,MATCH(C289,Data_Customers!$A$2:$A$602,0)) -> Housebuilder
A290: S000289 | B290: CAMP006 | C290: C00128 | D290: 0 | E290: 0 | F290: 0 | G290: 0 | H290: =INDEX(Data_Campaigns!$C$2:$C$10,MATCH(B290,Data_Campaigns!$A$2:$A$10,0)) -> Email | I290: =INDEX(Data_Customers!$C$2:$C$602,MATCH(C290,Data_Customers!$A$2:$A$602,0)) -> Housebuilder
A291: S000290 | B291: CAMP006 | C291: C00373 | D291: 1 | E291: 0 | F291: 0 | G291: 0 | H291: =INDEX(Data_Campaigns!$C$2:$C$10,MATCH(B291,Data_Campaigns!$A$2:$A$10,0)) -> Email | I291: =INDEX(Data_Customers!$C$2:$C$602,MATCH(C291,Data_Customers!$A$2:$A$602,0)) -> Housebuilder
A292: S000291 | B292: CAMP006 | C292: C00019 | D292: 1 | E292: 0 | F292: 0 | G292: 0 | H292: =INDEX(Data_Campaigns!$C$2:$C$10,MATCH(B292,Data_Campaigns!$A$2:$A$10,0)) -> Email | I292: =INDEX(Data_Customers!$C$2:$C$602,MATCH(C292,Data_Customers!$A$2:$A$602,0)) -> Housebuilder
A293: S000292 | B293: CAMP006 | C293: C00577 | D293: 0 | E293: 0 | F293: 0 | G293: 0 | H293: =INDEX(Data_Campaigns!$C$2:$C$10,MATCH(B293,Data_Campaigns!$A$2:$A$10,0)) -> Email | I293: =INDEX(Data_Customers!$C$2:$C$602,MATCH(C293,Data_Customers!$A$2:$A$602,0)) -> Housebuilder
... A517: S000516 | B517: CAMP008 | C517: C00523 | D517: 0 | E517: 0 | F517: 0 | G517: 0 | H517: =INDEX(Data_Campaigns!$C$2:$C$10,MATCH(B517,Data_Campaigns!$A$2:$A$10,0)) -> Email | I517: =INDEX(Data_Customers!$C$2:$C$602,MATCH(C517,Data_Customers!$A$2:$A$602,0)) -> Retail

Sheet Lookup_Tool
B2: Customer Lookup Tool
B3: Type a Customer ID into the yellow cell below — everything else updates automatically via INDEX/MATCH.
B5: Enter Customer ID: | C5: C00001
B7: Customer Name | C7: =IFERROR(INDEX(Data_Customers!$B$2:$B$602,MATCH($C$5,Data_Customers!$A$2:$A$602,0)),"Not found") -> Liam Evans
B8: Customer Type | C8: =IFERROR(INDEX(Data_Customers!$C$2:$C$602,MATCH($C$5,Data_Customers!$A$2:$A$602,0)),"") -> Retail
B9: Branch | C9: =IFERROR(INDEX(Data_Customers!$D$2:$D$602,MATCH($C$5,Data_Customers!$A$2:$A$602,0)),"") -> Binley (Coventry)
B10: Signup Date | C10: =IFERROR(INDEX(Data_Customers!$E$2:$E$602,MATCH($C$5,Data_Customers!$A$2:$A$602,0)),"") -> 45155
B11: Email Opt-in | C11: =IFERROR(INDEX(Data_Customers!$F$2:$F$602,MATCH($C$5,Data_Customers!$A$2:$A$602,0)),"") -> 1
B12: Total Lifetime Orders | C12: =COUNTIF(Data_Orders!$B$2:$B$4727,$C$5) -> 1
B13: Total Lifetime Spend | C13: =SUMIF(Data_Orders!$B$2:$B$4727,$C$5,Data_Orders!$E$2:$E$4727) -> 1873.59
B14: Average Order Value | C14: =IFERROR(SUMIF(Data_Orders!$B$2:$B$4727,$C$5,Data_Orders!$E$2:$E$4727)/COUNTIF(Data_Orders!$B$2:$B$4727,$C$5),0) -> 1873.59
B15: Most Recent Order Date | C15: =IFERROR(_xlfn.MAXIFS(Data_Orders!$C$2:$C$4727,Data_Orders!$B$2:$B$4727,$C$5),"No orders") -> 45504

Sheet Summary_BySegment
B2: Revenue & Margin by Customer Segment
B3: Pivot-style summary built with SUMIFS (a native Excel PivotTable can also be inserted from Data_OrderLines — see README).
B5: Customer Type | C5: Order Count | D5: Revenue | E5: Gross Margin ($) | F5: Margin %
B6: Contractor | C6: =COUNTIFS(Data_Orders!$F$2:$F$4727,B6) -> 1055 | D6: =SUMIFS(Data_OrderLines!$F$2:$F$14100,Data_OrderLines!$K$2:$K$14100,B6) -> 4605246.8 | E6: =SUMIFS(Data_OrderLines!$I$2:$I$14100,Data_OrderLines!$K$2:$K$14100,B6) -> 1368853.7 | F6: =IFERROR(E6/D6,0) -> 0.29723785
B7: Housebuilder | C7: =COUNTIFS(Data_Orders!$F$2:$F$4727,B7) -> 472 | D7: =SUMIFS(Data_OrderLines!$F$2:$F$14100,Data_OrderLines!$K$2:$K$14100,B7) -> 2083499.2 | E7: =SUMIFS(Data_OrderLines!$I$2:$I$14100,Data_OrderLines!$K$2:$K$14100,B7) -> 630698.76 | F7: =IFERROR(E7/D7,0) -> 0.30271131
B8: Retail | C8: =COUNTIFS(Data_Orders!$F$2:$F$4727,B8) -> 1554 | D8: =SUMIFS(Data_OrderLines!$F$2:$F$14100,Data_OrderLines!$K$2:$K$14100,B8) -> 6907346.8 | E8: =SUMIFS(Data_OrderLines!$I$2:$I$14100,Data_OrderLines!$K$2:$K$14100,B8) -> 2039530.9 | F8: =IFERROR(E8/D8,0) -> 0.2952698
B9: Trade Account | C9: =COUNTIFS(Data_Orders!$F$2:$F$4727,B9) -> 1644 | D9: =SUMIFS(Data_OrderLines!$F$2:$F$14100,Data_OrderLines!$K$2:$K$14100,B9) -> 7607321.4 | E9: =SUMIFS(Data_OrderLines!$I$2:$I$14100,Data_OrderLines!$K$2:$K$14100,B9) -> 2259034.1 | F9: =IFERROR(E9/D9,0) -> 0.29695526
B10: Total | C10: =SUM(C6:C9) -> 4725 | D10: =SUM(D6:D9) -> 21203414 | E10: =SUM(E6:E9) -> 6298117.5 | F10: =IFERROR(E10/D10,0) -> 0.29703318

Sheet Summary_ByBranch
B2: Revenue by Branch x Product Category
B3: Pivot-style summary built with SUMIFS.
B5: Branch \ Category | C5: Cement & Aggregates | D5: Insulation | E5: Landscaping | F5: Plumbing & Drainage | G5: Roofing | H5: Timber | I5: Tools & Fixings | J5: Total
B6: Binley (Coventry) | C6: =SUMIFS(Data_OrderLines!$F$2:$F$14100,Data_OrderLines!$L$2:$L$14100,$B6,Data_OrderLines!$H$2:$H$14100,C$5) -> 377431.22 | D6: =SUMIFS(Data_OrderLines!$F$2:$F$14100,Data_OrderLines!$L$2:$L$14100,$B6,Data_OrderLines!$H$2:$H$14100,D$5) -> 356834.03 | E6: =SUMIFS(Data_OrderLines!$F$2:$F$14100,Data_OrderLines!$L$2:$L$14100,$B6,Data_OrderLines!$H$2:$H$14100,E$5) -> 458608.65 | F6: =SUMIFS(Data_OrderLines!$F$2:$F$14100,Data_OrderLines!$L$2:$L$14100,$B6,Data_OrderLines!$H$2:$H$14100,F$5) -> 350394.21 | G6: =SUMIFS(Data_OrderLines!$F$2:$F$14100,Data_OrderLines!$L$2:$L$14100,$B6,Data_OrderLines!$H$2:$H$14100,G$5) -> 550930.35 | H6: =SUMIFS(Data_OrderLines!$F$2:$F$14100,Data_OrderLines!$L$2:$L$14100,$B6,Data_OrderLines!$H$2:$H$14100,H$5) -> 521704.47 | I6: =SUMIFS(Data_OrderLines!$F$2:$F$14100,Data_OrderLines!$L$2:$L$14100,$B6,Data_OrderLines!$H$2:$H$14100,I$5) -> 709809.91 | J6: =SUM(C6:I6) -> 3325712.8
B7: Birmingham South | C7: =SUMIFS(Data_OrderLines!$F$2:$F$14100,Data_OrderLines!$L$2:$L$14100,$B7,Data_OrderLines!$H$2:$H$14100,C$5) -> 364164.86 | D7: =SUMIFS(Data_OrderLines!$F$2:$F$14100,Data_OrderLines!$L$2:$L$14100,$B7,Data_OrderLines!$H$2:$H$14100,D$5) -> 411601.18 | E7: =SUMIFS(Data_OrderLines!$F$2:$F$14100,Data_OrderLines!$L$2:$L$14100,$B7,Data_OrderLines!$H$2:$H$14100,E$5) -> 492151.01 | F7: =SUMIFS(Data_OrderLines!$F$2:$F$14100,Data_OrderLines!$L$2:$L$14100,$B7,Data_OrderLines!$H$2:$H$14100,F$5) -> 490784.9 | G7: =SUMIFS(Data_OrderLines!$F$2:$F$14100,Data_OrderLines!$L$2:$L$14100,$B7,Data_OrderLines!$H$2:$H$14100,G$5) -> 549705.4 | H7: =SUMIFS(Data_OrderLines!$F$2:$F$14100,Data_OrderLines!$L$2:$L$14100,$B7,Data_OrderLines!$H$2:$H$14100,H$5) -> 498066.45 | I7: =SUMIFS(Data_OrderLines!$F$2:$F$14100,Data_OrderLines!$L$2:$L$14100,$B7,Data_OrderLines!$H$2:$H$14100,I$5) -> 764088.27 | J7: =SUM(C7:I7) -> 3570562.1
B8: Leicester | C8: =SUMIFS(Data_OrderLines!$F$2:$F$14100,Data_OrderLines!$L$2:$L$14100,$B8,Data_OrderLines!$H$2:$H$14100,C$5) -> 434442.75 | D8: =SUMIFS(Data_OrderLines!$F$2:$F$14100,Data_OrderLines!$L$2:$L$14100,$B8,Data_OrderLines!$H$2:$H$14100,D$5) -> 406511.8 | E8: =SUMIFS(Data_OrderLines!$F$2:$F$14100,Data_OrderLines!$L$2:$L$14100,$B8,Data_OrderLines!$H$2:$H$14100,E$5) -> 483876.65 | F8: =SUMIFS(Data_OrderLines!$F$2:$F$14100,Data_OrderLines!$L$2:$L$14100,$B8,Data_OrderLines!$H$2:$H$14100,F$5) -> 446982.33 | G8: =SUMIFS(Data_OrderLines!$F$2:$F$14100,Data_OrderLines!$L$2:$L$14100,$B8,Data_OrderLines!$H$2:$H$14100,G$5) -> 572884.33 | H8: =SUMIFS(Data_OrderLines!$F$2:$F$14100,Data_OrderLines!$L$2:$L$14100,$B8,Data_OrderLines!$H$2:$H$14100,H$5) -> 553025.09 | I8: =SUMIFS(Data_OrderLines!$F$2:$F$14100,Data_OrderLines!$L$2:$L$14100,$B8,Data_OrderLines!$H$2:$H$14100,I$5) -> 752090 | J8: =SUM(C8:I8) -> 3649813
B9: Northampton | C9: =SUMIFS(Data_OrderLines!$F$2:$F$14100,Data_OrderLines!$L$2:$L$14100,$B9,Data_OrderLines!$H$2:$H$14100,C$5) -> 464938.54 | D9: =SUMIFS(Data_OrderLines!$F$2:$F$14100,Data_OrderLines!$L$2:$L$14100,$B9,Data_OrderLines!$H$2:$H$14100,D$5) -> 457809.45 | E9: =SUMIFS(Data_OrderLines!$F$2:$F$14100,Data_OrderLines!$L$2:$L$14100,$B9,Data_OrderLines!$H$2:$H$14100,E$5) -> 492116.58 | F9: =SUMIFS(Data_OrderLines!$F$2:$F$14100,Data_OrderLines!$L$2:$L$14100,$B9,Data_OrderLines!$H$2:$H$14100,F$5) -> 452593.24 | G9: =SUMIFS(Data_OrderLines!$F$2:$F$14100,Data_OrderLines!$L$2:$L$14100,$B9,Data_OrderLines!$H$2:$H$14100,G$5) -> 576525.65 | H9: =SUMIFS(Data_OrderLines!$F$2:$F$14100,Data_OrderLines!$L$2:$L$14100,$B9,Data_OrderLines!$H$2:$H$14100,H$5) -> 588649.54 | I9: =SUMIFS(Data_OrderLines!$F$2:$F$14100,Data_OrderLines!$L$2:$L$14100,$B9,Data_OrderLines!$H$2:$H$14100,I$5) -> 814314.52 | J9: =SUM(C9:I9) -> 3846947.5
B10: Nuneaton | C10: =SUMIFS(Data_OrderLines!$F$2:$F$14100,Data_OrderLines!$L$2:$L$14100,$B10,Data_OrderLines!$H$2:$H$14100,C$5) -> 381513.44 | D10: =SUMIFS(Data_OrderLines!$F$2:$F$14100,Data_OrderLines!$L$2:$L$14100,$B10,Data_OrderLines!$H$2:$H$14100,D$5) -> 397254.48 | E10: =SUMIFS(Data_OrderLines!$F$2:$F$14100,Data_OrderLines!$L$2:$L$14100,$B10,Data_OrderLines!$H$2:$H$14100,E$5) -> 495769.55 | F10: =SUMIFS(Data_OrderLines!$F$2:$F$14100,Data_OrderLines!$L$2:$L$14100,$B10,Data_OrderLines!$H$2:$H$14100,F$5) -> 395623.55 | G10: =SUMIFS(Data_OrderLines!$F$2:$F$14100,Data_OrderLines!$L$2:$L$14100,$B10,Data_OrderLines!$H$2:$H$14100,G$5) -> 542593.4 | H10: =SUMIFS(Data_OrderLines!$F$2:$F$14100,Data_OrderLines!$L$2:$L$14100,$B10,Data_OrderLines!$H$2:$H$14100,H$5) -> 462183.73 | I10: =SUMIFS(Data_OrderLines!$F$2:$F$14100,Data_OrderLines!$L$2:$L$14100,$B10,Data_OrderLines!$H$2:$H$14100,I$5) -> 675484.81 | J10: =SUM(C10:I10) -> 3350423
B11: Rugby | C11: =SUMIFS(Data_OrderLines!$F$2:$F$14100,Data_OrderLines!$L$2:$L$14100,$B11,Data_OrderLines!$H$2:$H$14100,C$5) -> 394181.95 | D11: =SUMIFS(Data_OrderLines!$F$2:$F$14100,Data_OrderLines!$L$2:$L$14100,$B11,Data_OrderLines!$H$2:$H$14100,D$5) -> 417798.76 | E11: =SUMIFS(Data_OrderLines!$F$2:$F$14100,Data_OrderLines!$L$2:$L$14100,$B11,Data_OrderLines!$H$2:$H$14100,E$5) -> 456877.46 | F11: =SUMIFS(Data_OrderLines!$F$2:$F$14100,Data_OrderLines!$L$2:$L$14100,$B11,Data_OrderLines!$H$2:$H$14100,F$5) -> 421884.51 | G11: =SUMIFS(Data_OrderLines!$F$2:$F$14100,Data_OrderLines!$L$2:$L$14100,$B11,Data_OrderLines!$H$2:$H$14100,G$5) -> 582217.71 | H11: =SUMIFS(Data_OrderLines!$F$2:$F$14100,Data_OrderLines!$L$2:$L$14100,$B11,Data_OrderLines!$H$2:$H$14100,H$5) -> 490064.82 | I11: =SUMIFS(Data_OrderLines!$F$2:$F$14100,Data_OrderLines!$L$2:$L$14100,$B11,Data_OrderLines!$H$2:$H$14100,I$5) -> 696930.7 | J11: =SUM(C11:I11) -> 3459955.9
B12: Total | C12: =SUM(C6:C11) -> 2416672.8 | D12: =SUM(D6:D11) -> 2447809.7 | E12: =SUM(E6:E11) -> 2879399.9 | F12: =SUM(F6:F11) -> 2558262.7 | G12: =SUM(G6:G11) -> 3374856.8 | H12: =SUM(H6:H11) -> 3113694.1 | I12: =SUM(I6:I11) -> 4412718.2 | J12: =SUM(J6:J11) -> 21203414

Sheet Summary_CampaignROI
B2: Campaign Performance & ROI
B3: Pivot-style summary built with SUMIFS/COUNTIFS.
B5: Campaign | C5: Channel | D5: Cost | E5: Sends | F5: Opens | G5: Clicks | H5: Conversions | I5: Revenue Generated | J5: Open Rate | K5: Conversion Rate | L5: ROI %
B6: =Data_Campaigns!B2 -> Spring Trade Promo | C6: =Data_Campaigns!C2 -> Email | D6: =Data_Campaigns!F2 -> 2135.44 | E6: =COUNTIFS(Data_CampaignSends!$B$2:$B$518,Data_Campaigns!A2) -> 57 | F6: =COUNTIFS(Data_CampaignSends!$B$2:$B$518,Data_Campaigns!A2,Data_CampaignSends!$D$2:$D$518,1) -> 25 | G6: =COUNTIFS(Data_CampaignSends!$B$2:$B$518,Data_Campaigns!A2,Data_CampaignSends!$E$2:$E$518,1) -> 8 | H6: =COUNTIFS(Data_CampaignSends!$B$2:$B$518,Data_Campaigns!A2,Data_CampaignSends!$F$2:$F$518,1) -> 0 | I6: =SUMIFS(Data_CampaignSends!$G$2:$G$518,Data_CampaignSends!$B$2:$B$518,Data_Campaigns!A2) -> 0 | J6: =IFERROR(F6/E6,0) -> 0.43859649 | K6: =IFERROR(H6/E6,0) -> 0 | L6: =IFERROR((I6-D6)/D6,0) -> -1
B7: =Data_Campaigns!B3 -> Loft Insulation Push | C7: =Data_Campaigns!C3 -> Email | D7: =Data_Campaigns!F3 -> 463.88 | E7: =COUNTIFS(Data_CampaignSends!$B$2:$B$518,Data_Campaigns!A3) -> 33 | F7: =COUNTIFS(Data_CampaignSends!$B$2:$B$518,Data_Campaigns!A3,Data_CampaignSends!$D$2:$D$518,1) -> 11 | G7: =COUNTIFS(Data_CampaignSends!$B$2:$B$518,Data_Campaigns!A3,Data_CampaignSends!$E$2:$E$518,1) -> 6 | H7: =COUNTIFS(Data_CampaignSends!$B$2:$B$518,Data_Campaigns!A3,Data_CampaignSends!$F$2:$F$518,1) -> 0 | I7: =SUMIFS(Data_CampaignSends!$G$2:$G$518,Data_CampaignSends!$B$2:$B$518,Data_Campaigns!A3) -> 0 | J7: =IFERROR(F7/E7,0) -> 0.33333333 | K7: =IFERROR(H7/E7,0) -> 0 | L7: =IFERROR((I7-D7)/D7,0) -> -1
B8: =Data_Campaigns!B4 -> Contractor Loyalty Rewards | C8: =Data_Campaigns!C4 -> SMS | D8: =Data_Campaigns!F4 -> 445.65 | E8: =COUNTIFS(Data_CampaignSends!$B$2:$B$518,Data_Campaigns!A4) -> 67 | F8: =COUNTIFS(Data_CampaignSends!$B$2:$B$518,Data_Campaigns!A4,Data_CampaignSends!$D$2:$D$518,1) -> 30 | G8: =COUNTIFS(Data_CampaignSends!$B$2:$B$518,Data_Campaigns!A4,Data_CampaignSends!$E$2:$E$518,1) -> 8 | H8: =COUNTIFS(Data_CampaignSends!$B$2:$B$518,Data_Campaigns!A4,Data_CampaignSends!$F$2:$F$518,1) -> 1 | I8: =SUMIFS(Data_CampaignSends!$G$2:$G$518,Data_CampaignSends!$B$2:$B$518,Data_Campaigns!A4) -> 244.12 | J8: =IFERROR(F8/E8,0) -> 0.44776119 | K8: =IFERROR(H8/E8,0) -> 0.014925373 | L8: =IFERROR((I8-D8)/D8,0) -> -0.45221586
B9: =Data_Campaigns!B5 -> New Account Welcome Series | C9: =Data_Campaigns!C5 -> Email | D9: =Data_Campaigns!F5 -> 2039.3 | E9: =COUNTIFS(Data_CampaignSends!$B$2:$B$518,Data_Campaigns!A5) -> 35 | F9: =COUNTIFS(Data_CampaignSends!$B$2:$B$518,Data_Campaigns!A5,Data_CampaignSends!$D$2:$D$518,1) -> 18 | G9: =COUNTIFS(Data_CampaignSends!$B$2:$B$518,Data_Campaigns!A5,Data_CampaignSends!$E$2:$E$518,1) -> 8 | H9: =COUNTIFS(Data_CampaignSends!$B$2:$B$518,Data_Campaigns!A5,Data_CampaignSends!$F$2:$F$518,1) -> 4 | I9: =SUMIFS(Data_CampaignSends!$G$2:$G$518,Data_CampaignSends!$B$2:$B$518,Data_Campaigns!A5) -> 1302.53 | J9: =IFERROR(F9/E9,0) -> 0.51428571 | K9: =IFERROR(H9/E9,0) -> 0.11428571 | L9: =IFERROR((I9-D9)/D9,0) -> -0.36128574
B10: =Data_Campaigns!B6 -> Summer Landscaping Sale | C10: =Data_Campaigns!C6 -> Direct Mail | D10: =Data_Campaigns!F6 -> 1455.1 | E10: =COUNTIFS(Data_CampaignSends!$B$2:$B$518,Data_Campaigns!A6) -> 88 | F10: =COUNTIFS(Data_CampaignSends!$B$2:$B$518,Data_Campaigns!A6,Data_CampaignSends!$D$2:$D$518,1) -> 0 | G10: =COUNTIFS(Data_CampaignSends!$B$2:$B$518,Data_Campaigns!A6,Data_CampaignSends!$E$2:$E$518,1) -> 0 | H10: =COUNTIFS(Data_CampaignSends!$B$2:$B$518,Data_Campaigns!A6,Data_CampaignSends!$F$2:$F$518,1) -> 5 | I10: =SUMIFS(Data_CampaignSends!$G$2:$G$518,Data_CampaignSends!$B$2:$B$518,Data_Campaigns!A6) -> 2455.86 | J10: =IFERROR(F10/E10,0) -> 0 | K10: =IFERROR(H10/E10,0) -> 0.056818182 | L10: =IFERROR((I10-D10)/D10,0) -> 0.68776029
B11: =Data_Campaigns!B7 -> Housebuilder Bulk Discount | C11: =Data_Campaigns!C7 -> Email | D11: =Data_Campaigns!F7 -> 1614.39 | E11: =COUNTIFS(Data_CampaignSends!$B$2:$B$518,Data_Campaigns!A7) -> 34 | F11: =COUNTIFS(Data_CampaignSends!$B$2:$B$518,Data_Campaigns!A7,Data_CampaignSends!$D$2:$D$518,1) -> 18 | G11: =COUNTIFS(Data_CampaignSends!$B$2:$B$518,Data_Campaigns!A7,Data_CampaignSends!$E$2:$E$518,1) -> 1 | H11: =COUNTIFS(Data_CampaignSends!$B$2:$B$518,Data_Campaigns!A7,Data_CampaignSends!$F$2:$F$518,1) -> 0 | I11: =SUMIFS(Data_CampaignSends!$G$2:$G$518,Data_CampaignSends!$B$2:$B$518,Data_Campaigns!A7) -> 0 | J11: =IFERROR(F11/E11,0) -> 0.52941176 | K11: =IFERROR(H11/E11,0) -> 0 | L11: =IFERROR((I11-D11)/D11,0) -> -1
B12: =Data_Campaigns!B8 -> Winter Roofing Materials Offer | C12: =Data_Campaigns!C8 -> SMS | D12: =Data_Campaigns!F8 -> 2255.4 | E12: =COUNTIFS(Data_CampaignSends!$B$2:$B$518,Data_Campaigns!A8) -> 73 | F12: =COUNTIFS(Data_CampaignSends!$B$2:$B$518,Data_Campaigns!A8,Data_CampaignSends!$D$2:$D$518,1) -> 35 | G12: =COUNTIFS(Data_CampaignSends!$B$2:$B$518,Data_Campaigns!A8,Data_CampaignSends!$E$2:$E$518,1) -> 10 | H12: =COUNTIFS(Data_CampaignSends!$B$2:$B$518,Data_Campaigns!A8,Data_CampaignSends!$F$2:$F$518,1) -> 1 | I12: =SUMIFS(Data_CampaignSends!$G$2:$G$518,Data_CampaignSends!$B$2:$B$518,Data_Campaigns!A8) -> 749.7 | J12: =IFERROR(F12/E12,0) -> 0.47945205 | K12: =IFERROR(H12/E12,0) -> 0.01369863 | L12: =IFERROR((I12-D12)/D12,0) -> -0.66759777
B13: =Data_Campaigns!B9 -> Cement & Aggregates Flash Sale | C13: =Data_Campaigns!C9 -> Email | D13: =Data_Campaigns!F9 -> 1675.45 | E13: =COUNTIFS(Data_CampaignSends!$B$2:$B$518,Data_Campaigns!A9) -> 129 | F13: =COUNTIFS(Data_CampaignSends!$B$2:$B$518,Data_Campaigns!A9,Data_CampaignSends!$D$2:$D$518,1) -> 55 | G13: =COUNTIFS(Data_CampaignSends!$B$2:$B$518,Data_Campaigns!A9,Data_CampaignSends!$E$2:$E$518,1) -> 9 | H13: =COUNTIFS(Data_CampaignSends!$B$2:$B$518,Data_Campaigns!A9,Data_CampaignSends!$F$2:$F$518,1) -> 0 | I13: =SUMIFS(Data_CampaignSends!$G$2:$G$518,Data_CampaignSends!$B$2:$B$518,Data_Campaigns!A9) -> 0 | J13: =IFERROR(F13/E13,0) -> 0.42635659 | K13: =IFERROR(H13/E13,0) -> 0 | L13: =IFERROR((I13-D13)/D13,0) -> -1
